{
  "name": "Voodoo Mask",
  "cost": 650,
  "description": "A mask tuned to sip the arcane bindings that pass between caster and foe.",
  "abilities": [
    {
      "name": "Magic Lifesteal",
      "type": "passive",
      "description": "Restores the wielder's health for a portion of damage dealt by magical and physical spell damage. The lifesteal value is reduced by a factor of 0.2 against creeps."
    }
  ],
  "buildsInto": [
    "Veil of Discord",
    "Revenant's Brooch"
  ],
  "sellValue": 325
}
